mywordle/Wordle.py
mywordle/__init__.py
mywordle/data/.DS_Store
mywordle/data/possible_guesses.txt
mywordle/data/possible_words.txt
mywordle-1.2.6.dist-info/METADATA
mywordle-1.2.6.dist-info/WHEEL
mywordle-1.2.6.dist-info/top_level.txt
mywordle-1.2.6.dist-info/RECORD
