Metadata-Version: 2.4
Name: mywordle
Version: 1.2.6
Summary: a package that brings Wordle to Python with exceptional customization and personlization
Author: Kevin Zhu
Author-email: kzhu2099@gmail.com
Maintainer: Kevin Zhu
Maintainer-email: kzhu2099@gmail.com
License: MIT License
Project-URL: Homepage, https://github.com/kzhu2099/My-Wordle
Project-URL: Issues, https://github.com/kzhu2099/My-Wordle/issues
Classifier: Development Status :: 5 - Production/Stable
Classifier: Intended Audience :: Developers
Classifier: Intended Audience :: End Users/Desktop
Classifier: License :: OSI Approved :: MIT License
Classifier: Natural Language :: English
Classifier: Operating System :: OS Independent
Classifier: Programming Language :: Python :: 3
Classifier: Topic :: Internet :: WWW/HTTP :: Dynamic Content :: News/Diary
Requires-Python: >=3.9
Requires-Dist: kzutil
